mongogettersetter/__init__.py
mongogettersetter-1.5.0.dist-info/METADATA
mongogettersetter-1.5.0.dist-info/WHEEL
mongogettersetter-1.5.0.dist-info/top_level.txt
mongogettersetter-1.5.0.dist-info/RECORD
