Metadata-Version: 2.1
Name: mongogettersetter
Version: 1.5.0
Summary: A clean way to handle MongoDB documents in Pythonic way
Home-page: https://git.selfmade.ninja/sibidharan/pymongogettersetter
Author: Sibidharan
Author-email: sibi@selfmade.ninja
License: MIT
Keywords: pymongo mongodb mongo mongogettersetter gettersetter getter setter
Classifier: Programming Language :: Python :: 3
Classifier: License :: OSI Approved :: MIT License
Classifier: Operating System :: OS Independent
Classifier: Development Status :: 4 - Beta
